dfsj.py
dfsj-0.1.1.dist-info/WHEEL
dfsj-0.1.1.dist-info/METADATA
dfsj-0.1.1.dist-info/RECORD
