Metadata-Version: 2.1
Name: dfsj
Version: 0.1.1
Summary: An amazing sample package! 
Home-page: https://github.com/dfsj66011/mypkg
License: UNKNOWN
Author: dfsj
Author-email: dfsj66011@gmail.com
Classifier: License :: OSI Approved :: Apache Software License
